st_blogpost_component/__init__.py
st_blogpost_component/frontend/build/asset-manifest.json
st_blogpost_component/frontend/build/bootstrap.min.css
st_blogpost_component/frontend/build/index.html
st_blogpost_component/frontend/build/static/js/2.115577ef.chunk.js
st_blogpost_component/frontend/build/static/js/2.115577ef.chunk.js.LICENSE.txt
st_blogpost_component/frontend/build/static/js/2.115577ef.chunk.js.map
st_blogpost_component/frontend/build/static/js/2.cc3b77fa.chunk.js
st_blogpost_component/frontend/build/static/js/2.cc3b77fa.chunk.js.LICENSE.txt
st_blogpost_component/frontend/build/static/js/2.cc3b77fa.chunk.js.map
st_blogpost_component/frontend/build/static/js/main.060e67f4.chunk.js
st_blogpost_component/frontend/build/static/js/main.060e67f4.chunk.js.map
st_blogpost_component/frontend/build/static/js/main.19002e51.chunk.js
st_blogpost_component/frontend/build/static/js/main.19002e51.chunk.js.map
st_blogpost_component/frontend/build/static/js/main.5833844e.chunk.js
st_blogpost_component/frontend/build/static/js/main.5833844e.chunk.js.map
st_blogpost_component/frontend/build/static/js/main.a8adb8b7.chunk.js
st_blogpost_component/frontend/build/static/js/main.a8adb8b7.chunk.js.map
st_blogpost_component/frontend/build/static/js/main.bbd810e7.chunk.js
st_blogpost_component/frontend/build/static/js/main.bbd810e7.chunk.js.map
st_blogpost_component/frontend/build/static/js/main.ecb92db9.chunk.js
st_blogpost_component/frontend/build/static/js/main.ecb92db9.chunk.js.map
st_blogpost_component/frontend/build/static/js/main.ff14e290.chunk.js
st_blogpost_component/frontend/build/static/js/main.ff14e290.chunk.js.map
st_blogpost_component/frontend/build/static/js/runtime-main.0f051bbb.js
st_blogpost_component/frontend/build/static/js/runtime-main.0f051bbb.js.map
st_blogpost_component-0.1.0.dist-info/LICENSE
st_blogpost_component-0.1.0.dist-info/METADATA
st_blogpost_component-0.1.0.dist-info/WHEEL
st_blogpost_component-0.1.0.dist-info/top_level.txt
st_blogpost_component-0.1.0.dist-info/RECORD
