Metadata-Version: 2.1
Name: st-blogpost-component
Version: 0.1.0
Summary: UNKNOWN
Home-page: UNKNOWN
Author: YM
Author-email: 
License: UNKNOWN
Platform: UNKNOWN
Requires-Python: >=3.6
License-File: LICENSE
Requires-Dist: streamlit (>=0.63)
